formance/__init__.py
formance/formance.py
formance-0.1.0.dist-info/WHEEL
formance-0.1.0.dist-info/METADATA
formance-0.1.0.dist-info/RECORD
