Metadata-Version: 2.1
Name: formance
Version: 0.1.0
Summary: 
Home-page: https://github.com/limonyellow/formance
License: MIT
Author: limonyellow
Author-email: lemon@example.com
Requires-Python: >=3.9,<4.0
Classifier: License :: OSI Approved :: MIT License
Classifier: Programming Language :: Python :: 3
Classifier: Programming Language :: Python :: 3.10
Classifier: Programming Language :: Python :: 3.9
Requires-Dist: pytest (>=7.0.0,<8.0.0)
Project-URL: Repository, https://github.com/limonyellow/formance
